webhookhelper/__init__.py
webhookhelper/core.py
webhookhelper/discord_embed.py
webhookhelper-2.0.dist-info/licenses/LICENSE
webhookhelper-2.0.dist-info/METADATA
webhookhelper-2.0.dist-info/WHEEL
webhookhelper-2.0.dist-info/top_level.txt
webhookhelper-2.0.dist-info/RECORD
