Metadata-Version: 2.4
Name: webhookhelper
Version: 2.0
Summary: A simple helper to send webhooks to Discord and Telegram
Author-email: NotOfficial <root@notoff.pro>
License:                                  Apache License
Project-URL: Homepage, https://github.com/NotOfficals/WebHookHelper
Requires-Python: >=3.7
License-File: LICENSE
Dynamic: license-file
